setup_headers/__init__.py
setup_headers/_version.py
setup_headers/command.py
setup_headers/main.py
setup_headers/process.py
jfaleiro.setup_headers-0.0.4.dist-info/entry_points.txt
jfaleiro.setup_headers-0.0.4.dist-info/LICENSE
jfaleiro.setup_headers-0.0.4.dist-info/WHEEL
jfaleiro.setup_headers-0.0.4.dist-info/METADATA
jfaleiro.setup_headers-0.0.4.dist-info/RECORD
