Metadata-Version: 2.1
Name: jfaleiro.setup-headers
Version: 0.0.4
Summary: Automatic maintenance of licensing information in headers of source files.
Home-page: https://gitlab.com/jfaleiro.open/setup_headers
License: AGPL-3.0-or-later
Author: Jorge M Faleiro Jr
Author-email: j@falei.ro
Requires-Python: >=3.6.1,<4.0.0
Classifier: Development Status :: 4 - Beta
Classifier: Intended Audience :: Developers
Classifier: License :: OSI Approved :: GNU Affero General Public License v3
Classifier: License :: OSI Approved :: GNU Affero General Public License v3 or later (AGPLv3+)
Classifier: Operating System :: OS Independent
Classifier: Programming Language :: Python
Classifier: Programming Language :: Python :: 3
Classifier: Programming Language :: Python :: 3.7
Classifier: Programming Language :: Python :: 3.8
Classifier: Programming Language :: Python :: 3.9
Classifier: Topic :: Software Development
Classifier: Topic :: Software Development :: Libraries :: Python Modules
Provides-Extra: coverage
Provides-Extra: interactive-dev
Provides-Extra: tests
Requires-Dist: Cerberus (>=1.3.4,<2.0.0)
Requires-Dist: PyHamcrest (>=2.0.2,<3.0.0); extra == "tests" or extra == "coverage"
Requires-Dist: PyYAML (>=5.4.1,<6.0.0)
Requires-Dist: autopep8 (>=1.5.5,<2.0.0); extra == "interactive-dev"
Requires-Dist: behave (>=1.2.6,<2.0.0); extra == "tests"
Requires-Dist: coverage (>=5.4,<6.0); extra == "coverage"
Requires-Dist: flake8 (>=3.8.4,<4.0.0); extra == "interactive-dev"
Requires-Dist: glom (>=20.11.0,<21.0.0)
Requires-Dist: isort (>=5.7.0,<6.0.0); extra == "interactive-dev"
Requires-Dist: pre-commit (>=2.10.1,<3.0.0); extra == "interactive-dev"
Requires-Dist: pylint (>=2.7.0,<3.0.0)
Requires-Dist: pytest (>=6.2.2,<7.0.0); extra == "tests" or extra == "coverage"
Requires-Dist: rope (>=0.18.0,<0.19.0); extra == "interactive-dev"
